README.md
setup.py
NlpToolkit_UniversalDependencyParser.egg-info/PKG-INFO
NlpToolkit_UniversalDependencyParser.egg-info/SOURCES.txt
NlpToolkit_UniversalDependencyParser.egg-info/dependency_links.txt
NlpToolkit_UniversalDependencyParser.egg-info/requires.txt
NlpToolkit_UniversalDependencyParser.egg-info/top_level.txt
Parser/__init__.py
Parser/TransitionBasedParser/Agenda.py
Parser/TransitionBasedParser/ArcEagerInstanceGenerator.py
Parser/TransitionBasedParser/ArcEagerOracle.py
Parser/TransitionBasedParser/ArcEagerTransitionParser.py
Parser/TransitionBasedParser/ArcStandardOracle.py
Parser/TransitionBasedParser/ArcStandardTransitionParser.py
Parser/TransitionBasedParser/Candidate.py
Parser/TransitionBasedParser/Command.py
Parser/TransitionBasedParser/Decision.py
Parser/TransitionBasedParser/InstanceGenerator.py
Parser/TransitionBasedParser/Oracle.py
Parser/TransitionBasedParser/RandomOracle.py
Parser/TransitionBasedParser/RandomScoringOracle.py
Parser/TransitionBasedParser/ScoringOracle.py
Parser/TransitionBasedParser/SimpleInstanceGenerator.py
Parser/TransitionBasedParser/StackRelation.py
Parser/TransitionBasedParser/StackWord.py
Parser/TransitionBasedParser/State.py
Parser/TransitionBasedParser/TransitionParser.py
Parser/TransitionBasedParser/TransitionSystem.py
Parser/TransitionBasedParser/__init__.py