Metadata-Version: 2.1
Name: NlpToolkit-UniversalDependencyParser
Version: 1.0.0
Summary: Universal Dependency Parsing
Home-page: https://github.com/StarlangSoftware/UniversalDependencyParser-Py
Author: olcaytaner
Author-email: olcay.yildiz@ozyegin.edu.tr
License: UNKNOWN
Platform: UNKNOWN
